divyam_llm_interop/__init__.py
divyam_llm_interop/config/__init__.py
divyam_llm_interop/config/translate/__init__.py
divyam_llm_interop/config/translate/chat/__init__.py
divyam_llm_interop/config/translate/chat/capabilities/cohere.yaml
divyam_llm_interop/config/translate/chat/capabilities/deepseek.yaml
divyam_llm_interop/config/translate/chat/capabilities/falcon.yaml
divyam_llm_interop/config/translate/chat/capabilities/gemini.yaml
divyam_llm_interop/config/translate/chat/capabilities/gemma-2.yaml
divyam_llm_interop/config/translate/chat/capabilities/gemma-3.yaml
divyam_llm_interop/config/translate/chat/capabilities/llama.yaml
divyam_llm_interop/config/translate/chat/capabilities/mistral.yaml
divyam_llm_interop/config/translate/chat/capabilities/mpt.yaml
divyam_llm_interop/config/translate/chat/capabilities/openai.yaml
divyam_llm_interop/config/translate/chat/capabilities/others.yaml
divyam_llm_interop/config/translate/chat/capabilities/phi.yaml
divyam_llm_interop/config/translate/chat/capabilities/universal.yaml
divyam_llm_interop/config/translate/chat/capabilities/yi.yaml
divyam_llm_interop/config/translate/chat/models/cohere.yaml
divyam_llm_interop/config/translate/chat/models/deepseek.yaml
divyam_llm_interop/config/translate/chat/models/falcon.yaml
divyam_llm_interop/config/translate/chat/models/gemini.yaml
divyam_llm_interop/config/translate/chat/models/gemma.yaml
divyam_llm_interop/config/translate/chat/models/llama.yaml
divyam_llm_interop/config/translate/chat/models/mistral.yaml
divyam_llm_interop/config/translate/chat/models/mpt.yaml
divyam_llm_interop/config/translate/chat/models/openai.yaml
divyam_llm_interop/config/translate/chat/models/others.yaml
divyam_llm_interop/config/translate/chat/models/phi.yaml
divyam_llm_interop/config/translate/chat/models/qwen.yaml
divyam_llm_interop/config/translate/chat/models/yi.yaml
divyam_llm_interop/interop_logging.py
divyam_llm_interop/py.typed
divyam_llm_interop/translate/__init__.py
divyam_llm_interop-0.1.1.dist-info/METADATA
divyam_llm_interop-0.1.1.dist-info/WHEEL
divyam_llm_interop-0.1.1.dist-info/licenses/LICENSE
divyam_llm_interop-0.1.1.dist-info/licenses/LICENSE_HEADER.txt
divyam_llm_interop-0.1.1.dist-info/RECORD
