Metadata-Version: 2.4
Name: divyam-llm-interop
Version: 0.1.1
Summary: A lightweight, provider-neutral library for translating LLM requests and responses across model APIs.
License: Apache-2.0
License-File: LICENSE
License-File: LICENSE_HEADER.txt
Author: DivyamAI Technologies Private Limited
Requires-Python: >=3.10,<4.0
Classifier: License :: OSI Approved :: Apache Software License
Classifier: Operating System :: OS Independent
Classifier: Programming Language :: Python :: 3
Classifier: Programming Language :: Python :: 3.10
Classifier: Programming Language :: Python :: 3.11
Classifier: Programming Language :: Python :: 3.12
Classifier: Programming Language :: Python :: 3.13
Classifier: Programming Language :: Python :: 3.14
Classifier: Typing :: Typed
Requires-Dist: poetry-core (>=2.0.0)
Requires-Dist: pyyaml (>=6.0.3)
Requires-Dist: typing-extensions (>=4.15.0,<5.0.0)
Project-URL: Homepage, https://github.com/Divyam-AI/divyam-llm-interop
Project-URL: Issues, https://github.com/Divyam-AI/divyam-llm-interop/issues
Project-URL: Source, https://github.com/Divyam-AI/divyam-llm-interop
